{
    "generation1": {
        "plot": "李雷和韩梅梅是高中同学，韩梅梅的成绩一直很优秀，但李雷的成绩却一直在下滑。韩梅梅决定帮助李雷提高成绩，两人约在图书馆复习功课。",
        "chat_history": [
            "李雷：梅梅，谢谢你愿意帮我复习，我真的很感激。",
            "韩梅梅：别客气，李雷，咱们是同学嘛，互相帮助是应该的。",
            "李雷：可是我的成绩一直很差，怕拖累你。",
            "韩梅梅：不会的，只要你肯努力，一定会进步的。",
            "李雷：那好吧，我们先从哪一科开始？",
            "韩梅梅：我觉得你数学有点薄弱，我们先从数学开始吧。",
            "李雷：嗯，好。这个题目我不会做，你能教教我吗？",
            "韩梅梅：（耐心地讲解）这个题目其实不难，你看，这里要用到二次方程的解法。",
            "李雷：哦，原来是这样！我明白了。",
            "韩梅梅：对，就是这样。你再试试这道题。",
            "李雷：（尝试解题）嗯……我好像还是有点不太明白。",
            "韩梅梅：没关系，我们再来一遍，这次你仔细看。",
            "李雷：好，我会认真看的。",
            "韩梅梅：（重新讲解）这个步骤很重要，你要特别注意。",
            "李雷：哦，原来是这样！谢谢你，梅梅。",
            "韩梅梅：不客气，咱们再来一题吧，熟能生巧。",
            "李雷：好，我试试。（认真解题）",
            "韩梅梅：（微笑）嗯，进步很大，这次你做得很好。",
            "李雷：真的？太好了！",
            "韩梅梅：当然是真的，我什么时候骗过你。",
            "李雷：梅梅，你真厉害，要不是你，我还在迷糊呢。",
            "韩梅梅：别这么说，主要还是你自己肯努力。",
            "李雷：嗯，我会继续努力的。",
            "韩梅梅：那我们今天就先到这里吧，下次再继续。",
            "李雷：好的，梅梅。你今天真是帮了我大忙。",
            "韩梅梅：没事，我也很高兴能帮到你。",
            "李雷：那我送你回家吧。",
            "韩梅梅：不用了，我自己回去就行。",
            "李雷：没关系的，反正我也没事。",
            "韩梅梅：好吧，那谢谢你。",
            "李雷：不用谢，梅梅。"
        ],
        "facts": [
            "李雷成绩下滑，韩梅梅决定帮他复习功课",
            "两人约在图书馆复习，韩梅梅耐心讲解题目",
            "李雷经过学习，数学有所进步",
            "韩梅梅鼓励李雷，李雷表示会继续努力",
            "两人结束复习，李雷送韩梅梅回家"
        ]
    },
    "generation2": {
        "plot": "王大明是一名侦探，这天接到一个奇怪的委托，有人要他调查一件20年前的旧案。这案子涉及一个失踪的女孩和一座荒废的老宅。",
        "chat_history": [
            "王大明：你说你要我调查一件20年前的旧案？",
            "委托人：是的，这件事对我来说非常重要。",
            "王大明：具体是什么情况，你能详细说说吗？",
            "委托人：20年前，我的妹妹突然失踪了。她最后一次出现是在一座老宅附近。",
            "王大明：老宅？那地方现在怎么样了？",
            "委托人：已经荒废很久了，没有人敢靠近那里。",
            "王大明：为什么没人敢靠近？",
            "委托人：因为那里一直流传着各种诡异的传闻，有人说那地方闹鬼。",
            "王大明：哼，闹鬼？我只相信证据。那么你知道什么线索吗？",
            "委托人：当时警方也调查过，但什么都没找到。唯一的线索就是她的手帕，被发现时上面有一些奇怪的符号。",
            "王大明：符号？你有那手帕吗？",
            "委托人：有的，我一直保留着。",
            "王大明：好的，我需要看看那个手帕。",
            "委托人：（拿出手帕）就是这个，上面的符号我一直搞不懂。",
            "王大明：（仔细查看手帕）这些符号看起来像是一种古老的文字，可能需要找专家鉴定。",
            "委托人：你觉得这些符号能解开她失踪的谜团吗？",
            "王大明：不排除这种可能性，我会先找专家看看。",
            "委托人：谢谢你，王大明。希望你能找到她。",
            "王大明：这是我的工作，我会尽力的。",
            "（王大明走访了几位古文字专家，但都没有结果）",
            "王大明：看来这些符号确实不简单。",
            "助手小李：大明哥，我们接下来怎么办？",
            "王大明：我们去那座老宅看看，说不定会有新的发现。",
            "（两人来到老宅，发现了一些旧报纸和照片）",
            "王大明：这些旧报纸和照片也许能提供一些线索。",
            "助手小李：大明哥，你看这张照片，上面好像有那个女孩。",
            "王大明：嗯，这张照片确实很奇怪。我们需要查清楚这些照片的来源。",
            "助手小李：好的，我马上去查。",
            "（经过一番调查，发现照片是一个摄影师拍的）",
            "王大明：我们去找这个摄影师，他也许知道些什么。",
            "（找到摄影师后）",
            "摄影师：这些照片确实是我拍的，但我记得当时那女孩好像很害怕什么。",
            "王大明：害怕什么？",
            "摄影师：我也说不清楚，只是感觉她一直在躲避什么人。",
            "王大明：谢谢你的线索，我们会继续调查。",
            "（回到办公室）",
            "王大明：看来事情并不简单，我们需要更深入的调查。",
            "助手小李：明白，大明哥。"
        ],
        "facts": [
            "王大明接到委托，调查20年前的失踪案",
            "委托人妹妹20年前失踪，最后出现地点是一座老宅",
            "老宅荒废多年，流传着诡异传闻",
            "唯一线索是失踪女孩的手帕，上面有奇怪符号",
            "王大明找专家鉴定符号，但没有结果",
            "王大明决定去老宅调查，发现旧报纸和照片",
            "照片中有失踪女孩的身影，决定追查照片来源",
            "找到摄影师，得知女孩当时很害怕，像是在躲避什么人",
            "王大明决定继续深入调查"
        ]
    },
    "generation3": {
        "plot": "古代武侠世界，侠客李逍遥偶然得知一个神秘组织正在策划一场惊天阴谋。他决定深入调查，揭开真相。",
        "chat_history": [
            "李逍遥：据说江湖上最近出现了一个神秘组织，他们在策划什么大事。",
            "酒馆老板：你说的是“天影教”吧？他们可不好惹。",
            "李逍遥：天影教？我倒要看看他们到底在搞什么鬼。",
            "酒馆老板：年轻人，别乱来，天影教的手段可不是闹着玩的。",
            "李逍遥：谢谢提醒，我自有分寸。",
            "（李逍遥在城中四处打听，终于找到一个知情人）",
            "知情人：你想打听天影教的事？那可要小心点。",
            "李逍遥：多谢老哥，您知道些什么？",
            "知情人：天影教最近在招兵买马，听说他们要搞一件大事。",
            "李逍遥：什么大事？",
            "知情人：具体我也不清楚，但听说跟皇室有关。",
            "李逍遥：皇室？事情看来不简单。",
            "知情人：是啊，你要是打算调查，最好小心点。",
            "李逍遥：多谢老哥提醒，我会小心的。",
            "（李逍遥潜入天影教的一个据点，发现了他们的计划）",
            "李逍遥：原来他们的目标是皇宫，企图颠覆朝廷。",
            "天影教教徒：谁在那里！",
            "李逍遥：（迅速躲避）糟糕，被发现了。",
            "天影教教徒：快抓住他！",
            "李逍遥：（展开激战，击退教徒）看来我要尽快把消息传出去。",
            "（李逍遥赶回城中，找到官府）",
            "李逍遥：大人，有紧急情况要报告。",
            "官府大人：什么情况？",
            "李逍遥：天影教企图颠覆朝廷，他们的计划已经开始了。",
            "官府大人：什么！情况属实吗？",
            "李逍遥：属实，我亲眼所见。",
            "官府大人：这事非同小可，我马上向上级汇报。",
            "李逍遥：大人务必尽快，否则后果不堪设想。",
            "官府大人：你放心，我会立即行动。",
            "（官府展开行动，成功粉碎了天影教的阴谋）",
            "李逍遥：总算把这件事解决了。",
            "官府大人：这次多亏了你，李侠客。",
            "李逍遥：这是我应该做的，江湖安危，人人有责。"
        ],
        "facts": [
            "李逍遥得知神秘组织天影教策划阴谋",
            "天影教目标是颠覆朝廷",
            "李逍遥深入调查，发现计划",
            "天影教计划涉及皇室",
            "李逍遥向官府报告，官府采取行动",
            "官府成功粉碎天影教阴谋",
            "李逍遥表示江湖安危人人有责"
        ]
    }
}