{
    "generation1": {
        "plot": "刘伟和李佳是一对夫妻，最近因为刘伟沉迷手机游戏，李佳感到被冷落。这天晚上，李佳忍不住和刘伟摊牌。",
        "chat_history": [
            "李佳：刘伟，你能不能放下你的手机，咱们谈谈。",
            "刘伟：又怎么了？我就玩会儿游戏，放松一下。",
            "李佳：放松一下？你每天都在放松，可有想过我的感受吗？",
            "刘伟：你这话说的，我又没做什么对不起你的事。",
            "李佳：你每天回家就盯着手机，连个正眼都不给我。你觉得这样对吗？",
            "刘伟：我也是上了一天班，回家放松一下不行吗？",
            "李佳：放松可以，但你能不能有点时间留给我？我们已经很久没有好好说过话了。",
            "刘伟：你这话说的，我不是一直在家吗？",
            "李佳：在家？你人在家，心却不在家。你知道我有多孤单吗？",
            "刘伟：行行行，我知道了。那你说怎么办吧？",
            "李佳：我希望你能多关心我，别老是盯着手机。我们可以一起做些事情，比如看电影或者散步。",
            "刘伟：好吧，那我以后少玩一点，多陪陪你。",
            "李佳：你能这么想就好。希望这次你说的话能兑现。",
            "刘伟：放心吧，我一定会改的。",
            "李佳：你知道吗？我有时候真的觉得自己像个透明人。",
            "刘伟：对不起，是我忽略了你的感受。",
            "李佳：我不是要你道歉，我只是希望我们能像以前那样，彼此关心。",
            "刘伟：我明白了。以后我会多花时间陪你，不会再让你感到孤单。",
            "李佳：希望你说到做到。我们可以一起制定一些计划，比如每周一起做点什么。",
            "刘伟：好主意。这样我们的生活也会更有趣。",
            "李佳：你说得对。其实我也不想总是抱怨，只是希望我们能更幸福。",
            "刘伟：我知道了。咱们一起努力，让生活变得更美好。",
            "李佳：嗯，咱们一起加油。",
            "刘伟：那今晚我们一起看个电影吧？我请你吃爆米花。",
            "李佳：好啊。希望这次你能坚持下去，不要再让我失望。",
            "刘伟：一定一定。我会尽全力让你开心的。",
            "李佳：那就好。我们重新开始，好好过日子。",
            "刘伟：没问题。从现在开始，我会多花时间在你身上。",
            "李佳：谢谢你。我们一起努力。",
            "刘伟：那我们现在就去选电影吧。希望你喜欢。",
            "李佳：好的。希望我们的未来越来越好。"
        ],
        "facts": [
            "刘伟沉迷手机游戏，冷落了妻子李佳。",
            "李佳忍不住和刘伟摊牌，希望他多关心自己。",
            "刘伟承诺以后少玩游戏，多陪李佳。",
            "李佳希望两人能重新开始，制定一些共同的计划。",
            "刘伟同意了，并提议一起看电影。",
            "两人决定一起努力，让生活变得更美好。"
        ]
    },
    "generation2": {
        "plot": "张涛是一个年轻的警察，正在调查一起离奇的绑架案。这天，他和搭档小王到案发现场附近进行调查。",
        "chat_history": [
            "张涛：小王，你觉得这个绑架案有什么特别的地方吗？",
            "小王：我觉得这个案子不像是普通的绑架，似乎有更深的背景。",
            "张涛：你是说背后有更大的阴谋？",
            "小王：没错。被绑架的人身份不简单，可能涉及到商业机密。",
            "张涛：这样的话，我们得更加小心。先去现场看看有没有新的线索。",
            "小王：好的，走吧。",
            "（两人来到案发现场，四处查看）",
            "张涛：你看，这里有些奇怪的脚印，好像是故意留下的。",
            "小王：确实。我觉得绑匪可能想误导我们。",
            "张涛：那我们得仔细分析一下这些脚印。也许能找到一些有用的信息。",
            "小王：可这些脚印看起来像是杂乱无章的，怎么分析？",
            "张涛：别急，我们可以一步一步来。先拍照记录下来。",
            "小王：好的，我来拍照。",
            "（小王拍照留证留）",
            "张涛：还有，这里有一颗子弹壳，应该是绑匪留下的。",
            "小王：这颗子弹壳可能是重要线索。",
            "张涛：我们得分析一下这颗子弹壳的来源，也许能找到绑匪的踪迹。",
            "小王：好的，我会尽快送到实验室。",
            "张涛：除了这些，我们还需要查查附近的监控录像，看看有没有可疑人物。",
            "小王：我去调取监控录像。",
            "张涛：好，辛苦你了。希望能找到一些有用的信息。",
            "（小王去调取监控录像，张涛继续现场调查）",
            "小王：张涛，我发现了一些可疑的人物。他们在案发前后出现过。",
            "张涛：太好了。我们得尽快找到这些人。",
            "小王：我会去追查他们的身份。",
            "张涛：好的，我们不能放过任何一个线索。",
            "小王：放心吧，我会全力以赴。",
            "张涛：这次的案子很复杂，我们得更加小心谨慎。",
            "小王：明白，我们一起努力。",
            "张涛：好，继续查下去。希望早点破案。"
        ],
        "facts": [
            "张涛和小王正在调查一起离奇的绑架案。",
            "小王认为绑架案背后有更深的背景。",
            "两人在案发现场发现了一些奇怪的脚印和一颗子弹壳。",
            "张涛决定分析脚印和子弹壳，希望找到线索。",
            "小王调取监控录像，发现了一些可疑人物。",
            "两人决定继续追查这些线索，尽快破案。"
        ]
    },
    "generation3": {
        "plot": "李云是一个古代江湖侠客，这天他在一处茶馆遇到了老朋友赵明，两人多年未见，聊起了各自的经历。",
        "chat_history": [
            "李云：赵明！真的是你吗？多少年没见了！",
            "赵明：李云！真的是你！太久了，我都快认不出你了。",
            "李云：哈哈，是啊。自从那次分别，我们就没再见过面。",
            "赵明：你这些年都去哪了？听说你成了名震江湖的大侠。",
            "李云：哪里哪里，我不过是个浪迹天涯的游侠而已。",
            "赵明：别谦虚了。江湖中到处都是你的传说。",
            "李云：行了，别夸我了。你呢？这些年过得怎么样？",
            "赵明：我啊，还是老样子，在家乡开了个小茶馆，过得还算平静。",
            "李云：那挺好的。江湖虽然精彩，但也很危险。",
            "赵明：确实。你这些年有没有遇到什么大麻烦？",
            "李云：呵呵，麻烦多了去了。不过还好，我都挺过来了。",
            "赵明：说来听听，反正我们今天有的是时间。",
            "李云：好吧。去年在南方，我碰上了一伙恶徒，他们在欺压百姓。",
            "赵明：然后呢？你出手相救了？",
            "李云：是啊。我和那伙恶徒大战了一场，最后把他们都打败了。",
            "赵明：真是好样的！不愧是我认识的李云。",
            "李云：哈哈，你也别夸我了。我不过是尽了自己的本分。",
            "赵明：你这样的人，要是江湖上多几个就好了。",
            "李云：江湖本就险恶，但我们这些人，总要做点什么。",
            "赵明：说得对。对了，你接下来有什么打算？",
            "李云：我想暂时回家乡，休息一段时间。",
            "赵明：那正好，我们可以多聚聚。我还有好多话要跟你说呢。",
            "李云：好啊。我们好好喝几杯，聊个痛快。",
            "赵明：没问题。我这茶馆虽然不大，但茶还是不错的。",
            "李云：我相信。你这个老朋友，我可是一直记挂着。",
            "赵明：我也是。你不知道，我经常想起我们年轻时候的日子。",
            "李云：是啊，那时候无忧无虑，真是怀念。",
            "赵明：不过现在也不错。我们都经历了很多，变得更成熟了。",
            "李云：没错。经历让人成长，也让人更懂得珍惜。",
            "赵明：说得对。来，为我们的重逢干一杯。",
            "李云：干杯！愿我们友谊长存，江湖再见。",
            "赵明：友谊长存，江湖再见！"
        ],
        "facts": [
            "李云是一个古代江湖侠客，多年未见老朋友赵明。",
            "赵明开了一家小茶馆，生活平静。",
            "李云讲述自己在江湖上的经历，包括与恶徒的战斗。",
            "赵明对李云的侠义精神表示钦佩。",
            "李云打算回家乡休息一段时间。",
            "两人决定多聚聚，为重逢感到高兴。"
        ]
    }
}