{
    "generation1": {
        "plot": "小李是一个年轻的程序员，有一天他穿越到了一个充满魔法的奇幻世界。在这里，他遇到了一个神秘的女巫丽莎，并被卷入了一场拯救世界的冒险。",
        "chat_history": [
            "小李：这是哪里？我记得我在加班写代码，怎么突然到了这个地方？",
            "丽莎：你终于来了，小李。我们需要你的帮助。",
            "小李：你是谁？怎么知道我的名字？",
            "丽莎：我是丽莎，一个女巫。你的到来是预言中的一部分，你是那个被选中的人。",
            "小李：选中？什么选中？我只是个普通的程序员啊。",
            "丽莎：不，你有特殊的才能。只有你才能破解魔法之书中的密码，拯救我们的世界。",
            "小李：听起来像是小说里的情节，但我应该怎么做？",
            "丽莎：跟我来，我们需要先找到魔法之书。",
            "小李：好吧，反正我现在也不知道该怎么办。希望这只是一场梦。",
            "丽莎：这不是梦，这是现实。快跟上，我们没时间了。",
            "（两人穿越森林，来到一座古老的城堡）",
            "丽莎：魔法之书就在这里，但被黑暗法师守护着。",
            "小李：黑暗法师？听起来不妙啊。",
            "丽莎：别担心，我会掩护你。你只需要专注于破解密码。",
            "小李：好吧，我会尽力的。",
            "（两人进入城堡，遭遇黑暗法师的攻击）",
            "黑暗法师：哈哈哈，你们以为能从我这里拿走魔法之书吗？",
            "丽莎：小李，快去破解密码，我来挡住他！",
            "小李：好的，给我点时间。",
            "（小李全神贯注地研究魔法之书，丽莎与黑暗法师激战）",
            "小李：我好像找到了一些线索！",
            "丽莎：快点！我撑不了多久了！",
            "小李：解开了！魔法之书的秘密是……“爱”。",
            "黑暗法师：不可能！你怎么会知道这个秘密？",
            "丽莎：太好了，小李！我们打败了他！",
            "小李：怎么回事？为什么“爱”是秘密？",
            "丽莎：因为爱是最强大的魔法。感谢你，小李，我们的世界得救了。",
            "小李：这真是太不可思议了。现在我可以回家了吗？",
            "丽莎：当然，你已经完成了你的使命。再见，小李。",
            "（一道光芒闪过，小李回到了现实世界）",
            "小李：天哪，原来这真的不是梦。希望丽莎他们一切都好。",
            "（小李继续着他的程序员生活，但心中多了一份对奇幻世界的怀念）"
        ],
        "facts": [
            "小李穿越到了一个奇幻世界，遇到了女巫丽莎。",
            "丽莎告诉小李他是拯救世界的被选中人。",
            "小李需要破解魔法之书中的密码来拯救世界。",
            "两人来到古老的城堡，遭遇黑暗法师的攻击。",
            "小李成功破解密码并发现“爱”是魔法之书的秘密。",
            "黑暗法师被打败，世界得救。",
            "小李完成使命，回到了现实世界。"
        ]
    },
    "generation2": {
        "plot": "老张是一个退休的警察，平时喜欢钓鱼。一天，他在河边钓鱼时，发现了一具浮尸。他立刻报警，并决定协助破案。",
        "chat_history": [
            "老张：喂，110吗？这里是河边，我发现了一具浮尸。",
            "接警员：请保持现场，不要移动尸体，我们马上派人过去。",
            "老张：好的，我会在这里等你们。",
            "（警察到达现场，封锁周围）",
            "警察A：老张，你怎么在这里？",
            "老张：我在钓鱼，没想到会遇到这种事。",
            "警察B：你发现了什么？",
            "老张：尸体看起来已经泡了很久，应该是被水冲到这里的。",
            "警察A：我们需要你的帮助，老张。你有丰富的办案经验。",
            "老张：当然，我愿意帮忙。",
            "（法医到达现场，开始检验尸体）",
            "法医：死因是溺水，但尸体上有明显的外伤痕迹。",
            "老张：看来这是一起谋杀案。",
            "警察B：我们需要调查附近的监控，看看有没有可疑人物。",
            "老张：我认识这附近的居民，可以帮忙打听一下。",
            "（老张开始走访附近居民）",
            "老张：李大爷，最近有没有看到什么可疑的人或事？",
            "李大爷：前几天晚上，好像有一辆陌生的车在河边停了很久。",
            "老张：你还记得车牌号吗？",
            "李大爷：记不清了，但车子是黑色的，车牌尾号好像是7。",
            "老张：谢谢你，这很重要。",
            "（老张回到警局，与警察们分享信息）",
            "老张：我走访了周围居民，有人看到一辆黑色的车子，车牌尾号是7。",
            "警察A：那我们查一下附近的监控，看看能不能找到这辆车。",
            "（警方调取监控，发现了可疑车辆）",
            "警察B：找到了，这辆车曾在案发时间出现在河边。",
            "老张：我们需要找到车主，查清楚他和死者的关系。",
            "（警方根据车牌找到了车主，并将其带回警局）",
            "车主：我什么都不知道，我只是停车休息了一下。",
            "老张：别狡辩，我们已经有证据证明你和这起案件有关。",
            "车主：好吧，我说实话，我是被人雇来处理尸体的。",
            "警察A：是谁雇你的？",
            "车主：我不知道他的名字，只知道他给了我很多钱…",
            "老张：我们需要继续追查这个幕后黑手。",
            "（警方继续调查，最终抓获了真正的凶手）",
            "老张：总算破案了，这次真是个大案子。",
            "警察B：谢谢你，老张，没有你的帮助，我们不会这么快破案。",
            "老张：不用谢，这就是我应该做的。"
        ],
        "facts": [
            "老张在河边发现了一具浮尸并报警。",
            "警方到达现场，发现尸体有外伤痕迹。",
            "老张协助警方走访附近居民，收集线索。",
            "居民提供了可疑车辆的信息。",
            "警方通过监控找到了可疑车辆，并锁定车主。",
            "车主承认被雇来处理尸体，警方继续追查幕后黑手。",
            "最终，警方抓获了真正的凶手，案件成功告破。"
        ]
    },
    "generation3": {
        "plot": "小王是一个年轻的科学家，他的研究成果被同事小李窃取并用于申请专利。小王发现后，决定维护自己的权益，与小李展开了一场激烈的斗争。",
        "chat_history": [
            "小王：小李，这个专利是我的研究成果，你为什么要偷走它？",
            "小李：别胡说，你有证据吗？",
            "小王：我有实验记录和数据，一切都能证明这是我的成果。",
            "小李：那又怎样？现在专利是我的名字，你能把我怎么样？",
            "小王：我会向公司举报你的行为，你等着吧！",
            "小李：随便你，公司是不会相信你的。",
            "（小王向公司举报，提交证据）",
            "公司主管：小王，我们已经收到你的举报，会进行调查。",
            "小王：谢谢，我希望公司能公平处理这件事。",
            "（公司成立调查小组，开始调查）",
            "调查员：小李，我们需要检查你的实验记录。",
            "小李：什么？为什么要检查我的记录？",
            "调查员：这是公司的决定，请配合。",
            "（调查小组检查了小李的实验记录，发现了问题）",
            "调查员：小李，你的实验记录和小王的高度重合，解释一下。",
            "小李：这...这只是巧合！",
            "小王：巧合？你就是抄袭我的研究成果！",
            "公司主管：小李，根据调查结果，你确实存在剽窃行为。",
            "小李：不，这不可能！你们搞错了！",
            "公司主管：我们决定撤销你的专利申请，并给予相应处罚。",
            "小李：不！你们不能这样对我！",
            "小王：这就是你应得的，剽窃别人的劳动成果是要付出代价的。",
            "公司主管：小王，我们会重新审核你的专利申请，并补偿你的损失。",
            "小王：谢谢公司，我只是希望自己的努力不被辜负。",
            "（小李被公司处罚，失去了专利权）",
            "小李：小王，我恨你！",
            "小王：你恨我没用，这是你自作自受。",
            "小李：我不会就这么算了，你等着瞧！",
            "公司主管：小李，你已经违反了公司的规定，再继续闹事只会让事情更糟。",
            "小王：我只想继续我的研究，不想被这些事情打扰。",
            "公司主管：放心吧，小王，公司会支持你的工作。",
            "小李：你们会后悔的！",
            "小王：希望你能反省自己的行为，不要再做这样的事了。",
            "公司主管：好了，事情已经解决，希望你们都能专注于工作。",
            "小王：我会的，谢谢大家的支持。",
            "（小王重新开始了他的研究工作，事情终于平息了下来）"
        ],
        "facts": [
            "小王的研究成果被同事小李窃取并申请专利。",
            "小王向公司举报小李的行为，并提交证据。",
            "公司成立调查小组，开始调查小李的实验记录。",
            "调查结果证明小李剽窃了小王的研究成果。",
            "公司决定撤销小李的专利申请，并给予相应处罚。",
            "小李失去了专利权并被公司处罚。",
            "小王重新开始了他的研究工作，事情平息。"
        ]
    }
}