{
    "generation1": {
        "plot": "在一个宁静的小镇上，杰克和艾丽丝是一对青梅竹马，他们一起长大，但因某些误会分开多年。这天，杰克回到小镇，决定找艾丽丝聊聊，试图修复他们的友谊。",
        "chat_history": [
            "杰克：艾丽丝，好久不见。",
            "艾丽丝：杰克？你怎么会在这里？",
            "杰克：我回来了，想见见老朋友。",
            "艾丽丝：老朋友？我以为我们已经不是了。",
            "杰克：对不起，当初是我错了。我想解释。",
            "艾丽丝：解释？现在还有什么好解释的？",
            "杰克：当年我没有勇气面对那些流言蜚语，我选择了逃避。",
            "艾丽丝：你知道你那样做伤了我多深吗？",
            "杰克：我知道，所以我一直在自责。我回来就是想弥补。",
            "艾丽丝：弥补？你觉得这么多年一句对不起就够了吗？",
            "杰克：我知道一句对不起不足以弥补一切，但我希望能有机会重新开始。",
            "艾丽丝：重新开始？你真的认为我们能回到从前吗？",
            "杰克：不求回到从前，只希望我们能重新认识彼此。",
            "艾丽丝：唉...我也不知道该怎么说。你这几年过得怎么样？",
            "杰克：一直在外面闯荡，虽然赚了些钱，但内心一直不安。",
            "艾丽丝：钱不是问题，重要的是你有没有改变。",
            "杰克：我变了，变得更加成熟，更加懂得珍惜。",
            "艾丽丝：希望如此吧。但你要知道，信任是需要时间去恢复的。",
            "杰克：我愿意等，等到你能重新相信我。",
            "艾丽丝：好吧，我愿意给你一个机会。我们从朋友做起，慢慢来。",
            "杰克：谢谢你，艾丽丝。我一定不会再让你失望。",
            "艾丽丝：那我们就走走看吧，这个小镇也变化了不少。",
            "杰克：好，带我去看看我们曾经的回忆。",
            "艾丽丝：记得我们小时候最喜欢去的那片草地吗？",
            "杰克：当然记得，那是我们最快乐的时光。",
            "艾丽丝：嗯，希望这次回来你能找到内心的平静。",
            "杰克：有你在，我一定能做到。"
        ],
        "facts": [
            "杰克和艾丽丝是青梅竹马，但因误会分开多年",
            "杰克回到小镇，决定找艾丽丝聊聊，试图修复友谊",
            "杰克为当初的逃避向艾丽丝道歉，希望重新开始",
            "艾丽丝对杰克的回归感到困惑和怀疑",
            "杰克表达了他的改变和对重新认识彼此的愿望",
            "艾丽丝决定给杰克一个机会，从朋友做起，慢慢恢复信任"
        ]
    },
    "generation2": {
        "plot": "在未来的世界里，探险家莉莉和她的机器人助手阿尔法在寻找一块神秘的能源石。这块能源石据说能拯救他们濒临毁灭的星球。这天，他们在一片荒芜的沙漠中发现了能源石的线索。",
        "chat_history": [
            "莉莉：阿尔法，我们终于找到了能源石的线索！",
            "阿尔法：是的，主人。根据扫描，这个区域有强烈的能量波动。",
            "莉莉：太好了！我们赶快过去看看。",
            "阿尔法：小心，前方有不明生物的迹象。",
            "莉莉：不明生物？该不会是沙漠巨虫吧？",
            "阿尔法：很有可能。建议开启防护系统。",
            "莉莉：好的，防护系统开启。我们继续前进。",
            "（一阵沙尘暴袭来，能见度急剧下降）",
            "莉莉：该死的沙尘暴！阿尔法，你能确定能源石的位置吗？",
            "阿尔法：正在重新定位，请稍等。",
            "莉莉：我们必须快点，这里的环境太恶劣了。",
            "阿尔法：已确定位置，距离我们500米。",
            "莉莉：走！我们加快速度！",
            "（突然，沙漠巨虫从沙地中跃出）",
            "莉莉：小心！阿尔法，攻击模式！",
            "阿尔法：攻击模式启动。",
            "（激烈的战斗开始，莉莉和阿尔法合力击退沙漠巨虫）",
            "莉莉：呼，总算搞定了。",
            "阿尔法：主人，前方50米处发现能源石。",
            "莉莉：太棒了！我们成功了！",
            "（莉莉和阿尔法来到能源石前，开始采集）",
            "莉莉：这块能源石看起来比想象中还要大。",
            "阿尔法：是的，主人。这将是拯救星球的关键。",
            "莉莉：赶快采集完毕，我们要尽快返回基地。",
            "阿尔法：已完成采集，可以出发了。",
            "莉莉：好，出发！我们回家！"
        ],
        "facts": [
            "莉莉和她的机器人助手阿尔法在寻找神秘的能源石",
            "他们在沙漠中发现了能源石的线索",
            "遇到了沙漠巨虫的袭击，经过激烈战斗成功击退",
            "最终找到了能源石，并开始采集",
            "他们计划尽快返回基地拯救濒临毁灭的星球"
        ]
    },
    "generation3": {
        "plot": "在古代王国，勇士凯恩接到国王的命令，要去讨伐北方的叛军。这次任务对王国的安危至关重要。凯恩在出发前和他的挚友雷恩进行了深刻的对话。",
        "chat_history": [
            "凯恩：雷恩，我要出发了。",
            "雷恩：凯恩，保重啊。这次任务凶险异常。",
            "凯恩：是啊，但这是为了王国的安危，我义不容辞。",
            "雷恩：我知道，但你一定要小心。北方叛军可不是好对付的。",
            "凯恩：放心吧，我会谨慎行事的。",
            "雷恩：你有计划吗？怎么应对叛军的埋伏？",
            "凯恩：我们会从东侧突袭，趁他们不备。",
            "雷恩：希望一切顺利。你有我的支持，无论发生什么。",
            "凯恩：谢谢你，雷恩。你的支持对我很重要。",
            "雷恩：记得带上那块护身符，它会保佑你的。",
            "凯恩：我会的。这是我母亲留给我的，我一直带着。",
            "雷恩：好兄弟，祝你凯旋归来。",
            "凯恩：一定会的。我们很快就能再见。",
            "（凯恩出发，雷恩目送他离开）",
            "雷恩：凯恩，你一定要活着回来。",
            "凯恩：（回头）我会的，等我。",
            "（凯恩带领士兵出发，踏上征途）",
            "士兵：将军，我们准备好了。",
            "凯恩：好，出发！为了王国！",
            "士兵们：为了王国！",
            "（凯恩和士兵们消失在地平线）"
        ],
        "facts": [
            "勇士凯恩接到国王的命令，要讨伐北方叛军",
            "凯恩在出发前和挚友雷恩进行了深刻的对话",
            "凯恩计划从东侧突袭叛军",
            "雷恩给了凯恩一块护身符保佑他",
            "凯恩带领士兵出发，誓言为了王国的安危"
        ]
    }
}