{
    "generation1": {
        "plot": "老王是一个退休多年的老警察，最近因为社区里的连环失踪案被请回来协助调查。老王和他的前搭档小李一起，逐渐揭开了隐藏在社区多年的秘密。",
        "chat_history": [
            "老王：小李，这些失踪案的受害者有什么共同点吗？",
            "小李：目前来看，都是独居老人，且失踪前都接到过奇怪的电话。",
            "老王：奇怪的电话？能查到电话来源吗？",
            "小李：我们查过了，都是一次性手机，无法追踪。",
            "老王：这可不妙啊，看来对方非常小心。我们从受害者的生活圈入手，看看他们失踪前见过谁。",
            "小李：好的，我会尽快调取他们的通话记录和访客记录。",
            "老王：另外，再去问问社区的老人，看有没有人也接到过类似的电话。",
            "小李：明白，我这就去办。",
            "（小李离开后，老王在档案室里翻阅旧案卷）",
            "老王：这些年头的案件都没头绪，但直觉告诉我，这里面有些东西很不对劲。",
            "（小李回来）",
            "小李：老王，我找到了一些线索。有位老人说他接到电话后，对方让他去某个地点领钱，他感觉不对劲就没去。",
            "老王：领钱？看来对方是用钱引诱老人出门，真是卑鄙。",
            "小李：更糟糕的是，刚刚又有一个老人失踪了。",
            "老王：立即通知所有人，全力搜查！这次一定不能再让对方得逞！",
            "小李：是！我这就去安排。",
            "（几天后，老王和小李终于找到了失踪老人被关押的地方）",
            "老王：小李，小心点，可能有陷阱。",
            "小李：明白，我们小心行动。",
            "（两人冲入废弃工厂，救出了被绑架的老人）",
            "老人：谢谢你们！我以为自己再也见不到阳光了。",
            "老王：不用谢，这是我们的职责。你还记得是谁绑架你的吗？",
            "老人：他们都戴着面具，我看不清他们的样子。",
            "小李：没关系，您先休息，我们会继续追查。",
            "老王：小李，带老人回去休息，我们继续调查这里的线索。",
            "小李：好的，老王。",
            "（老王在工厂里发现了一本旧日记，上面记载着多年前的另一桩失踪案）",
            "老王：这本日记或许能揭开更多的秘密，我们得好好研究一下。",
            "（两人回到警局，开始研究日记和其他线索）",
            "小李：老王，这本日记提到的失踪案跟现在的情况很相似，看来这不是一时兴起，而是长期策划。",
            "老王：没错，我们要抓紧时间，不能再让更多人受害。"
        ],
        "facts": [
            "老王是退休多年的老警察，因社区连环失踪案被请回来协助调查。",
            "失踪案受害者都是独居老人，且失踪前接到过奇怪的电话。",
            "对方使用一次性手机，无法追踪。",
            "老王和小李从受害者的生活圈入手调查。",
            "对方用钱引诱老人出门，刚刚又有一个老人失踪。",
            "老王和小李在废弃工厂救出了被绑架的老人。",
            "老人无法辨认绑架者，因为他们戴着面具。",
            "老王在工厂里发现了一本旧日记，记录着多年前的失踪案。",
            "老王和小李认为这是长期策划的犯罪，需要抓紧时间继续调查。"
        ]
    },
    "generation2": {
        "plot": "小丽是一位年轻的实习医生，最近医院来了一个神秘的病人。这个病人似乎知道很多秘密，并不断向小丽透露一些离奇的故事。",
        "chat_history": [
            "病人：你是小丽吧？我听说你很有潜力。",
            "小丽：谢谢，您是？",
            "病人：我只是个普通病人，但我知道一些不普通的事情。",
            "小丽：什么事情？",
            "病人：你知道这个医院的地下室里藏着什么吗？",
            "小丽：地下室？那只是存放医疗器械的地方吧。",
            "病人：不，全都不是。那里藏着一些见不得光的东西。",
            "小丽：见不得光的东西？您到底在说什么？",
            "病人：你要是有胆量，就去看看。你会发现真相。",
            "（小丽半信半疑，但好奇心驱使她去地下室查看）",
            "小丽：这里确实有些奇怪的地方，怎么会有这么多老旧的设备？",
            "（小丽发现一扇隐藏的门，打开后看到了一些封存的文件）",
            "小丽：这些文件看起来像是几十年前的，为什么会藏在这里？",
            "（小丽回到病房）",
            "小丽：您说的是真的，我在地下室发现了一些老旧的文件。",
            "病人：那些文件上写的内容你看了吗？",
            "小丽：还没来得及细看，只知道是关于一些实验的。",
            "病人：那些实验曾经在这里进行，但因为出事被封存了。",
            "小丽：出事？什么样的实验？",
            "病人：你得自己去看，我不能说太多。",
            "小丽：我会去看的，但为什么您知道这些？",
            "病人：因为我曾经是这里的一员，这些事我亲眼所见。",
            "小丽：那您现在为什么在这里？",
            "病人：因为我也是那些实验的受害者之一。我回来是为了揭开真相。",
            "小丽：这太不可思议了，我得去向院长报告这件事。",
            "病人：小心，很多人不希望这些真相被揭露。"
        ],
        "facts": [
            "小丽是一位年轻的实习医生，医院来了一个神秘的病人。",
            "病人告诉小丽医院地下室里藏着秘密。",
            "小丽在地下室发现了一些老旧的文件，内容涉及实验。",
            "病人曾是实验的一员，也是受害者之一。",
            "小丽决定去向院长报告，但病人警告她要小心。"
        ]
    },
    "generation3": {
        "plot": "在一个奇幻的世界里，年轻的魔法学徒艾琳和她的导师凯尔被卷入了一场魔法战争。为了保护王国，他们必须找到传说中的上古神器。",
        "chat_history": [
            "艾琳：导师，我们真的要去寻找上古神器吗？那不是传说中的东西吗？",
            "凯尔：传说未必是虚构的，这次我们别无选择。只有上古神器能平息这场战争。",
            "艾琳：可是，我们对它一无所知，怎么找？",
            "凯尔：古老的预言中提到，神器藏在圣山之巅。我们要从那里开始。",
            "艾琳：圣山之巅？那是一个极其危险的地方！",
            "凯尔：是的，但我们没有退路。准备好你的行装，明天一早出发。",
            "（次日清晨，艾琳和凯尔踏上了前往圣山的旅途）",
            "艾琳：导师，这里到处都是魔兽，我们真的能找到圣山的入口吗？",
            "凯尔：别担心，我有地图。我们只需沿着指引前进。",
            "（途中，二人遭遇魔兽袭击）",
            "艾琳：小心！有魔兽！",
            "凯尔：用你的魔法防御，我来解决它们！",
            "（凯尔用强大的魔法击退了魔兽，艾琳则施展防御魔法保护他们）",
            "艾琳：好险啊，幸好有您在。",
            "凯尔：继续前进，我们不能在这里停留太久。",
            "（经过数日跋涉，他们终于到达圣山之巅）",
            "艾琳：看，那是预言中提到的石碑！",
            "凯尔：没错，上面刻着开启神器的方法。我们必须按照指示进行。",
            "（两人按照石碑上的指示，开启了隐藏的洞穴）",
            "艾琳：这里面好黑，导师，我们要小心。",
            "凯尔：别怕，我会照亮前路。",
            "（洞穴深处，他们终于找到了传说中的上古神器）",
            "艾琳：这就是上古神器？它看起来好普通。",
            "凯尔：外表普通，内含强大力量。快，我们得带它回去结束这场战争。",
            "艾琳：明白了，导师，我们回去吧。"
        ],
        "facts": [
            "艾琳和导师凯尔被卷入魔法战争，为保护王国，他们寻找上古神器。",
            "上古神器传说藏在圣山之巅。",
            "途中他们遭遇魔兽袭击，凯尔击退魔兽。",
            "他们在圣山之巅找到了开启神器的方法，进入洞穴发现神器。",
            "艾琳和凯尔决定带回神器结束战争。"
        ]
    }
}