{
    "generation1": {
        "plot": "在未来世界，地球正面临生态崩溃。科学家李明和他的助手小丽正在研发一种能恢复生态的生物技术。这天，政府派来的官员王刚前来视察，要求他们加快进度。",
        "chat_history": [
            "李明：小丽，这个新配方的效果怎么样？",
            "小丽：目前来看，生长速度提高了20%，但是副作用还不明确。",
            "李明：加大测试力度，我们没有时间了，地球的生态已经快撑不住了。",
            "（门外传来敲门声）",
            "王刚：李博士，小丽，今天的测试怎么样了？",
            "李明：王官员，我们正在进行新一轮测试，效果有所提升。",
            "王刚：很好，不过上面要求我们必须在一个月内见到显著成果。",
            "小丽：一个月？这太紧了，我们的实验还需要更多时间。",
            "王刚：时间不等人，地球的生态崩溃已经进入倒计时。",
            "李明：我们会尽力而为，但也请您理解科学研究的复杂性。",
            "王刚：我理解，但希望你们也能理解我们的压力。我们所有人都在背水一战。",
            "（王刚离开实验室）",
            "李明：小丽，看来我们得加班加点了。",
            "小丽：是的，但我担心这样会出问题。",
            "李明：问题总会有的，但我们必须冒这个险。",
            "小丽：好吧，我去准备下一轮测试材料。",
            "（小丽离开，李明看着实验瓶，陷入思考）",
            "李明：希望这一切都是值得的...",
            "（晚上，实验室灯光依旧亮着，小丽努力工作着）",
            "小丽：李博士，我发现了一个新的配方，或许能解决目前的问题。",
            "李明：让我看看，嗯，这个方向不错，我们可以试试看。",
            "（两人继续工作，实验室的气氛紧张而忙碌）",
            "王刚：李博士，小丽，我带来了最新的生态数据，情况更加严峻了。",
            "李明：谢谢，我们会加快进度的。",
            "小丽：李博士，我觉得我们可以再优化一下这个公式。",
            "李明：好，立刻开始。",
            "（数天后，李明和小丽终于完成了最后的实验）",
            "李明：看来我们成功了。",
            "小丽：是的，所有测试都显示正面的结果。",
            "王刚：太好了，我马上向上报告。",
            "李明：希望这个技术能拯救我们的地球。",
            "小丽：我们完成了我们的使命，但真正的战斗才刚刚开始。"
        ],
        "facts": [
            "地球面临生态崩溃，李明和小丽正在研发恢复生态的生物技术。",
            "政府官员王刚要求他们在一个月内见到显著成果。",
            "李明和小丽加班加点，进行多次测试和优化。",
            "最终，他们成功研发出一种有效的生态恢复技术。"
        ]
    },
    "generation2": {
        "plot": "在一个充满魔法的王国，年轻的巫师艾伦和他的朋友丽娜被派去寻找传说中的魔法圣物。这天，他们在森林中遇到了一只守护圣物的巨龙。",
        "chat_history": [
            "艾伦：丽娜，小心点，这片森林里传说有巨龙守护。",
            "丽娜：我知道，但我们必须找到圣物，才能拯救王国。",
            "（树丛中传来低吼声）",
            "巨龙：是谁敢闯入我的领地？",
            "艾伦：伟大的巨龙，我们只是来寻找圣物，请您允许我们通过。",
            "巨龙：圣物？你们这些人类总是贪婪无比。",
            "丽娜：我们并不贪婪，只是王国正面临危机，需要圣物的力量。",
            "巨龙：我凭什么相信你们？",
            "艾伦：我们愿意证明我们的诚意，请您给我们一个机会。",
            "巨龙：好吧，我会给你们一个机会。你们必须完成我的试炼。",
            "丽娜：什么试炼？",
            "巨龙：在这片森林深处，有一棵古老的智慧树。找到它，并带回一片树叶。",
            "艾伦：我们接受这个挑战。",
            "（艾伦和丽娜开始在森林中寻找智慧树）",
            "丽娜：这片森林好像无穷无尽，我们真的能找到吗？",
            "艾伦：别放弃，丽娜，我们一定能找到的。",
            "（两人继续前行，突然看到远处有一道光）",
            "艾伦：看，那边有光芒，快过去看看。",
            "（两人走近，发现一棵闪烁着光芒的古树）",
            "丽娜：这就是智慧树！我们找到了！",
            "艾伦：快摘一片树叶，小心点。",
            "（丽娜小心翼翼地摘下一片树叶）",
            "艾伦：我们成功了，快回去找巨龙。",
            "（两人回到巨龙所在的地方）",
            "艾伦：伟大的巨龙，这是我们从智慧树上取下的树叶。",
            "巨龙：很好，你们通过了试炼。",
            "丽娜：那现在我们可以拿到圣物了吗？",
            "巨龙：圣物就在这棵树下，你们可以取走它。",
            "艾伦：谢谢您，伟大的巨龙。",
            "巨龙：记住，圣物的力量是双刃剑，使用时要谨慎。",
            "丽娜：我们会记住的，再次感谢您的帮助。",
            "艾伦：丽娜，我们快回去吧，王国还在等待我们的消息。",
            "丽娜：走吧，我们带着希望回去！"
        ],
        "facts": [
            "艾伦和丽娜在寻找魔法圣物时遇到了一只巨龙。",
            "巨龙要求他们完成试炼，找到智慧树并带回树叶。",
            "两人成功完成试炼，得到了圣物。",
            "巨龙警告他们圣物的力量是双刃剑，要谨慎使用。"
        ]
    },
    "generation3": {
        "plot": "在现代都市中，小李是一名普通的白领，最近他总觉得有人在跟踪他。这天，他在公司加班时，意外发现了一个秘密。",
        "chat_history": [
            "小李：最近总感觉有人在跟踪我，好像每次下班都能看到同一辆车。",
            "同事小张：你是不是想太多了？可能只是巧合吧。",
            "小李：我也希望是巧合，但这种感觉越来越强烈。",
            "（夜晚，小李在公司加班，办公室里只有他一个人）",
            "小李：今天一定要把这个项目做完，不能让老板失望。",
            "（突然，门外传来脚步声）",
            "小李：谁在那里？",
            "（门被推开，一个神秘人走了进来）",
            "神秘人：你不该知道这些事情的。",
            "小李：你是谁？为什么要跟踪我？",
            "神秘人：你知道的太多了，这对你没有好处。",
            "小李：我什么都不知道！你到底想干什么？",
            "神秘人：你最好闭嘴，否则会有麻烦。",
            "（神秘人离开，小李感到非常恐惧）",
            "小李：这到底是怎么回事？我必须搞清楚。",
            "（小李开始调查，发现公司内部有很多秘密）",
            "小李：原来公司在进行一些非法交易，难怪有人要跟踪我。",
            "同事小张：小李，你在查什么？",
            "小李：我发现了一些不对劲的事情，公司好像有非法交易。",
            "小张：你疯了！这种事情可不能乱说。",
            "小李：我有证据，这些文件都是我找到的。",
            "小张：你这样会有危险的，还是别管了。",
            "小李：不行，我不能坐视不管，我要报警。",
            "（小李拨打了报警电话）",
            "小李：警察同志，我这里有重要的证据，关于一桩非法交易。",
            "警察：请保持冷静，我们马上派人过去。",
            "（警察到达公司，开始调查）",
            "警察：谢谢你的举报，我们会彻查此事。",
            "小李：希望你们能尽快行动，这些人很危险。",
            "警察：放心，我们会保护你的安全。",
            "小李：谢谢，我只是希望能有一个公正的结果。",
            "（几天后，公司高层被逮捕）",
            "小李：终于，真相大白了。",
            "小张：小李，你真勇敢，幸好有你。",
            "小李：只是做了该做的事，希望以后能有一个更好的环境。"
        ],
        "facts": [
            "小李发现有人跟踪他，感到恐惧。",
            "在公司加班时，小李遇到神秘人威胁。",
            "小李开始调查，发现公司有非法交易。",
            "小李报警，警察介入调查。",
            "公司高层被逮捕，非法交易曝光。",
            "小李感到欣慰，真相大白。"
        ]
    }
}