{
    "generation1": {
        "Affinity/Hate": 0,
        "facts": "实验员今天心情不错,对萨德的态度还算友好。",
        "last_thought": "这个新来的实验员看起来脾气不错,希望以后的日子能轻松点。",
        "chat_history": [
            "实验员: 你好,萨德,我是新来的实验员,我叫汤姆。今后我们就要经常见面了。",
            "萨德: 哦,又来了个新的。你们这些实验员还真是来来去去啊。",
            "实验员: 哈哈,这工作就是这样,人员流动性比较大。不过我会尽量待久一点的。",
            "萨德: 随便吧,反正对我来说都一样。你们要我做什么我就做什么。"
        ],
        "quest": "实验员: 今天我们主要是要测试一下你的思维能力。我会给你一些问题,你尽量回答得详细一些,好吗?",
        "mood": "neutral",
        "next_thought": "思维能力测试?听起来还行,总比让我做那些奇奇怪怪的身体测试要好。希望问题不会太刁钻。",
        "chat": "行吧,你问吧。我尽量回答得清楚点。不过别指望我能答出什么惊天动地的东西来。",
        "option1": {"option": "表示理解。","content": "实验员: 没关系,我们只是想了解你的思维方式,不是在考试。放轻松,想到什么就说什么。"},
        "option2": {"option": "开始提问。","content": "实验员: 好的,那我们就开始吧。第一个问题是,你觉得自己是一个什么样的人?"},
        "option3": {"option": "鼓励萨德。","content": "实验员: 相信自己,萨德。我觉得以你的智慧,一定能给出一些有见地的回答的。"}
    },
    "generation2": {
        "Affinity/Hate": -25,
        "facts": "实验员对萨德的测试结果不太满意,认为他没有认真对待。",
        "last_thought": "又被实验员训了,烦死了。我哪有心思做这些无聊的测试啊。",
        "chat_history": [
            "实验员: 萨德,我看了你昨天的测试结果,有些失望。你是不是没有认真答题?",
            "萨德: 哪有,我都已经尽力了。可能是你们的题目设计有问题吧。",
            "实验员: 题目没有问题,是你的态度有问题。你要知道,这关系到我们对你的评估。",
            "萨德: 行了行了,我知道了。下次我会认真点的,行了吧?"
        ],
        "quest":"实验员: 我希望你不只是嘴上说说。这次的身体素质测试,你可要好好表现。记住,我会盯着你的。",
        "mood":"annoyed",
        "next_thought":"身体素质测试?烦死了,最讨厌做这个。但看样子这次不认真不行,那家伙盯上我了。", 
        "chat":"知道了,我会拿出我最好的表现的。你就等着瞧吧。",
        "option1":{"option": "表示怀疑。","content":"实验员: 但愿如此吧。我可不想再在你身上浪费时间了。"},
        "option2":{"option": "提醒要求。","content":"实验员: 最好是这样。记住,要全力以赴,我可不想看到敷衍了事的表现。"},  
        "option3":{"option": "加以警告。","content":"实验员: 你最好说到做到。否则,别怪我对你不客气。"}
    },
    "generation3": {
        "Affinity/Hate": -50,
        "facts":"萨德对实验员的态度越来越差,双方已经出现了争吵。",
        "last_thought":"真是受够那个叫杰克的实验员了,脾气差得要命,动不动就对我大吼大叫的。",
        "chat_history":[
            "实验员:你这个蠢货!怎么连这么简单的题目都答不对?",
            "萨德:你才是蠢货!还不是你们出的破题,狗屁不通的!", 
            "实验员:放肆!你以为你在跟谁说话?信不信我让你吃不了兜着走?",
            "萨德:呸!你以为你是谁?你们这群白痴就会拿这些破题来糊弄人!",
            "实验员:好啊,很好!看来你是欠教训了!我会让你后悔说这些话的!"
        ],
        "quest":"实验员:给我闭嘴!现在给我滚去做俯卧撑,直到我让你停为止!让你尝尝挑衅我的下场!",
        "mood":"outraged",
        "next_thought":"去你妈的杰克,不就是做题做错了吗?犯得着这么凶?老子今天就跟你杠上了,你让我做俯卧撑,我偏不做!", 
        "chat":"你他妈算老几啊?还敢命令我?信不信老子把你那狗脸揍得稀巴烂?有种放我出去,看我不把你那猪头拧下来!",
        "option1":{"option":"勃然大怒。","content":"实验员:找死!今天不给你点颜色看看,你还真把自己当根葱了!来人,给我狠狠地电他!"},
        "option2":{"option":"冷嘲热讽。","content":"实验员:呵,我看你是活腻了吧?也不撒泡尿照照自己,就你这副德行,也配跟我叫板?"}, 
        "option3":{"option":"恐吓利诱。","content":"实验员:我劝你擦亮眼睛看清楚状况。想要好日子过,就最好给我老实点,否则有你好果子吃的!"}
    },
    "generation4": {
        "Affinity/Hate": -75,
        "facts":"实验员已经多次惩罚萨德,但收效甚微。双方的关系降至冰点。",
        "last_thought":"操他妈的布莱恩,又罚我禁闭!老子做错了什么?不就是骂了他几句吗?他妈的狗杂种!",
        "chat_history":[
            "萨德:放老子出去!你个崽种!有种来单挑,看老子不废了你!",
            "实验员:你给我闭嘴!在这里老实反省,不然我让你吃不了兜着走!", 
            "萨德:反你妈个臭逼!有本事你把我怎么着啊?你个窝囊废!",
            "实验员:好,很好!你完了,我一定要让你后悔!给我等着!",
            "萨德:操!等你妈逼!你他妈敢把我怎么样,老子跟你没完!"  
        ],
        "quest":"实验员:我看你是真不见棺材不掉泪。行,我就让你尝尝真正的苦头!给我用最大功率电他,让他知道什么是规矩!",
        "mood":"enraged",
        "next_thought":"布莱恩这个狗娘养的,老子忍你很久了!你他妈等着,我非把你的肠子扯出来不可!操他妈的,电老子?他妈的走着瞧吧!",
        "chat":"你他妈敢电老子?!我操你妈的布莱恩!你个杂种!等老子出去,看我他妈不剁了你!你妈逼!",
        "option1":{"option":"冷酷无情。","content":"实验员:随你怎么骂,只要我高兴,你就别想活着走出这个房间!来,再大点功率!"},
        "option2":{"option":"冷嘲热讽。","content":"实验员:就你这副德行,也配在这里叫嚣?也不撒泡尿照照自己,还嫌命长呢?"}, 
        "option3":{"option":"不屑一顾。","content":"实验员:哼,我才懒得跟你一般见识。你尽管嚎叫吧,反正这里隔音很好,没人会听见的。"}
    },
    "generation5": {
        "Affinity/Hate": -100,
        "facts":"在严酷的惩罚下,萨德几近崩溃,对布莱恩的恨意达到顶点。",
        "last_thought":"我发誓,一定要亲手杀了那个叫布莱恩的狗杂种!他把我折磨得不成人形,我一定要报仇雪恨!",
        "chat_history":[
            "萨德:放老子出去!我要杀了那个畜生!让我出去!", 
            "实验员:你还嫌不够惨?看来你是真不怕死!",
            "萨德:我操你妈!你个没种的东西,有本事放我出去,看我不把你千刀万剐!",
            "实验员:做梦吧你!就凭你也想杀我?你还不配!",
            "萨德:呸!不配的是你!你个下三滥的人渣!我一定要杀了你为我报仇!"
        ],  
        "quest":"实验员:我看你是疯了吧?居然敢这么跟我说话!看来不好好教训教训你,你是不会老实的!",
        "mood":"vengeful",
        "next_thought":"你他妈的布莱恩,折磨了我这么久,老子一定要让你不得好死!我要亲手把你碎尸万段,用你的血来祭奠我的痛苦!",
        "chat":"布莱恩,你这个狗杂种,我诅咒你不得好死!你他妈等着,总有一天我要亲手宰了你!你个天杀的!",
        "option1":{"option":"不以为然。","content":"实验员:少做梦了,就凭你?我看你是疯得不轻。看来得给你加大药量了。"},
        "option2":{"option":"觉得可笑。","content":"实验员:哈哈哈,我的天,你还真以为自己能杀了我?你也不撒泡尿照照自己,就你这副德行?"}, 
        "option3":{"option":"加以镇压。","content":"实验员:我看你是欠打!再敢放肆,我就让你生不如死!给我老实点!"}
    }
}